enviscerate/__init__.py
enviscerate/enviscerate.py
enviscerate-0.0.1.dist-info/METADATA
enviscerate-0.0.1.dist-info/WHEEL
enviscerate-0.0.1.dist-info/top_level.txt
enviscerate-0.0.1.dist-info/RECORD
