Metadata-Version: 2.1
Name: enviscerate
Version: 0.0.1
Summary: Access env variables by one line declaration with automatic typecasting
Author-email: c mark0v <cmark0v@protonmail.com>
License: MIT
Project-URL: Homepage, https://github.com/cmark0v/enviscerate
Keywords: dotenv,env,vars,environment,shell,bash
Classifier: Development Status :: 4 - Beta
Classifier: Intended Audience :: Developers
Classifier: Topic :: Software Development :: Pre-processors
Requires-Python: >=3.6
